ponfig
