Metadata-Version: 2.1
Name: ponfig
Version: 0.0.8
Summary: A simple configuration and environment management package.
Home-page: https://hollowdata.com
Author: zeturn
Author-email: hollowdata@outlook.com
Classifier: Programming Language :: Python :: 3
Classifier: License :: OSI Approved :: MIT License
Classifier: Operating System :: OS Independent
License-File: LICENSE
